fast_flights_unoff/__init__.py
fast_flights_unoff/_generated_enum.py
fast_flights_unoff/bright_data_fetch.py
fast_flights_unoff/cookies.proto
fast_flights_unoff/cookies_impl.py
fast_flights_unoff/cookies_pb2.py
fast_flights_unoff/core.py
fast_flights_unoff/decoder.py
fast_flights_unoff/fallback_playwright.py
fast_flights_unoff/filter.py
fast_flights_unoff/flights.proto
fast_flights_unoff/flights_impl.py
fast_flights_unoff/flights_pb2.py
fast_flights_unoff/local_playwright.py
fast_flights_unoff/primp.py
fast_flights_unoff/primp.pyi
fast_flights_unoff/py.typed
fast_flights_unoff/schema.py
fast_flights_unoff/search.py
fast_flights_unoff-0.2.0.dist-info/licenses/LICENSE
fast_flights_unoff-0.2.0.dist-info/WHEEL
fast_flights_unoff-0.2.0.dist-info/METADATA
fast_flights_unoff-0.2.0.dist-info/RECORD
