Metadata-Version: 2.4
Name: fast-flights-unoff
Version: 0.2.0
Summary: An unofficial, extended version of the fast, robust, strongly-typed Google Flights scraper (API).
Keywords: flights,google,google-flights,scraper,protobuf,travel,trip,passengers,airport
Author-email: atharvvvg <atharv230303@gmail.com>
Requires-Python: >=3.8
Classifier: Programming Language :: Python :: 3
Classifier: License :: OSI Approved :: MIT License
Classifier: Operating System :: OS Independent
License-File: LICENSE
Requires-Dist: primp
Requires-Dist: protobuf>=5.27.0
Requires-Dist: selectolax
Requires-Dist: playwright ; extra == "local"
Project-URL: Documentation, https://aweirddev.github.io/flights/
Project-URL: Issues, https://github.com/atharvvvg/google-flights-scraper/issues
Project-URL: Original Source, https://github.com/AWeirdDev/flights
Project-URL: Source, https://github.com/atharvvvg/google-flights-scraper
Provides-Extra: local
